rpicammqtt/__init__.py
rpicammqtt/__main__.py
rpicammqtt/configpt.py
rpicammqtt/loadconfig.py
rpicammqtt/pantilt.py
rpicammqtt/rpicammqtt.py
rpicammqtt/rpicamparser.py
rpicammqtt/servo.py
rpicammqtt/config/Adafruit_PCA9685.yaml
rpicammqtt/config/rpi-cam-mqtt.yaml
rpicammqtt/data/rpi-cam-info.json
rpicammqtt/systemd/rpi-cam-mqtt.service
rpicammqtt-0.10.1.dist-info/LICENSE
rpicammqtt-0.10.1.dist-info/METADATA
rpicammqtt-0.10.1.dist-info/WHEEL
rpicammqtt-0.10.1.dist-info/entry_points.txt
rpicammqtt-0.10.1.dist-info/top_level.txt
rpicammqtt-0.10.1.dist-info/RECORD
