Metadata-Version: 2.1
Name: rpicammqtt
Version: 0.10.1
Summary: Mqtt agent for rpi-cam-web-interface
Home-page: https://gitlab.com/gbus/rpi-cam-mqtt
Author: Gianluca Busiello
Author-email: gianluca.busiello@gmail.com
License: UNKNOWN
Platform: UNKNOWN
Classifier: Programming Language :: Python :: 3
Classifier: License :: OSI Approved :: Apache Software License
Classifier: Operating System :: POSIX :: Linux
Requires-Dist: PyYaml (>=3.12)
Requires-Dist: paho-mqtt (>=1.4.0)
Requires-Dist: adafruit-pca9685
